nse_nn_lpv/CNN_utils.py
nse_nn_lpv/__init__.py
nse_nn_lpv/nse_data_helpers.py
nse_nn_lpv/nse_fem_utils.py
nse_nn_lpv-1.0.1.dist-info/AUTHORS
nse_nn_lpv-1.0.1.dist-info/LICENSE
nse_nn_lpv-1.0.1.dist-info/METADATA
nse_nn_lpv-1.0.1.dist-info/WHEEL
nse_nn_lpv-1.0.1.dist-info/pbr.json
nse_nn_lpv-1.0.1.dist-info/top_level.txt
nse_nn_lpv-1.0.1.dist-info/RECORD
