Metadata-Version: 2.1
Name: nse-nn-lpv
Version: 1.0.1
Summary: Helper functions for NSE as LPV with Neural Networks
Home-page: https://gitlab.mpi-magdeburg.mpg.de/cnn-nse-ldlpv/21-nse-nn-lpv
Author: Jan Heiland
Author-email: jnhlnd@gmail.com
Maintainer: Jan Heiland
Maintainer-email: jnhlnd@gmail.com
License: MIT
Platform: UNKNOWN
Classifier: License :: OSI Approved :: MIT License
Classifier: Operating System :: OS Independent
Classifier: Programming Language :: Python
Classifier: Programming Language :: Python :: 3
Classifier: Programming Language :: Python :: 3.7
Requires-Dist: setuptools
Requires-Dist: pbr
Requires-Dist: rich
Requires-Dist: numpy
Requires-Dist: scipy
Requires-Dist: tikzplotlib
Requires-Dist: dolfin-navier-scipy (>=1.2.1)
Requires-Dist: multidim-galerkin-pod (>=1.0.3)
